dhc_search/__init__.py
dhc_sort/__init__.py
dsahelperforcp-0.0.4.dist-info/LICENSE.md
dsahelperforcp-0.0.4.dist-info/METADATA
dsahelperforcp-0.0.4.dist-info/WHEEL
dsahelperforcp-0.0.4.dist-info/top_level.txt
dsahelperforcp-0.0.4.dist-info/RECORD
