Metadata-Version: 2.1
Name: dsahelperforcp
Version: 0.0.4
Summary: This package contains important dats structures implementation and algorithms for CP
Home-page: UNKNOWN
Author: Vishal Reddy
Author-email: vishal126sw@gmail.com
License: UNKNOWN
Keywords: python,python3,competitive programming,cp,search,linear search
Platform: UNKNOWN
Classifier: Development Status :: 1 - Planning
Classifier: Intended Audience :: Developers
Classifier: Programming Language :: Python :: 3
Classifier: Operating System :: Unix
Classifier: Operating System :: MacOS :: MacOS X
Classifier: Operating System :: Microsoft :: Windows
License-File: LICENSE.md
